[
  {
    "productId": 1751754756929,
    "productTitle": "T-shirt USDC",
    "name": "Dmitrii",
    "address": "Cannes",
    "quantity": 1,
    "wallet": "0x693f7243e7577A3845364F23d856349f15571856",
    "sellerChainId": "6",
    "amount": 1,
    "id": 1751758600303,
    "status": "unpaid",
    "createdAt": "2025-07-05T23:36:40.303Z"
  },
  {
    "productId": 1751754756929,
    "productTitle": "T-shirt USDC",
    "name": "Dmitrii",
    "address": "Cannes",
    "quantity": 1,
    "wallet": "0x693f7243e7577A3845364F23d856349f15571856",
    "sellerChainId": "48900",
    "amount": 1,
    "id": 1751758629921,
    "status": "paid",
    "createdAt": "2025-07-05T23:37:09.921Z",
    "paidAt": "2025-07-05T23:37:33.569Z",
    "paidNetwork": "zircuit"
  },
  {
    "productId": 1751754756929,
    "productTitle": "T-shirt USDC",
    "name": "Dmitrii",
    "address": "Cannes",
    "quantity": 1,
    "wallet": "0x693f7243e7577A3845364F23d856349f15571856",
    "sellerChainId": "747",
    "amount": 1,
    "id": 1751758777821,
    "status": "unpaid",
    "createdAt": "2025-07-05T23:39:37.821Z"
  },
  {
    "productId": 1751754756929,
    "productTitle": "T-shirt USDC",
    "name": "Dmitrii",
    "address": "Cannes",
    "quantity": 1,
    "wallet": "0x693f7243e7577A3845364F23d856349f15571856",
    "sellerChainId": "747",
    "amount": 1,
    "id": 1751758886800,
    "status": "unpaid",
    "createdAt": "2025-07-05T23:41:26.800Z"
  }
]